test.py
Alogger/Alogger.py
Alogger/__init__.py
AloggerPy-1.1.dist-info/METADATA
AloggerPy-1.1.dist-info/WHEEL
AloggerPy-1.1.dist-info/entry_points.txt
AloggerPy-1.1.dist-info/top_level.txt
AloggerPy-1.1.dist-info/RECORD
